legend_pydataobj-1.17.2.dist-info/licenses/LICENSE
lgdo/__init__.py
lgdo/_version.py
lgdo/cli.py
lgdo/lgdo_utils.py
lgdo/logging.py
lgdo/units.py
lgdo/utils.py
lgdo/compression/__init__.py
lgdo/compression/base.py
lgdo/compression/generic.py
lgdo/compression/radware.py
lgdo/compression/utils.py
lgdo/compression/varlen.py
lgdo/lh5/__init__.py
lgdo/lh5/concat.py
lgdo/lh5/core.py
lgdo/lh5/datatype.py
lgdo/lh5/exceptions.py
lgdo/lh5/iterator.py
lgdo/lh5/settings.py
lgdo/lh5/store.py
lgdo/lh5/tools.py
lgdo/lh5/utils.py
lgdo/lh5/_serializers/__init__.py
lgdo/lh5/_serializers/read/__init__.py
lgdo/lh5/_serializers/read/array.py
lgdo/lh5/_serializers/read/composite.py
lgdo/lh5/_serializers/read/encoded.py
lgdo/lh5/_serializers/read/ndarray.py
lgdo/lh5/_serializers/read/scalar.py
lgdo/lh5/_serializers/read/utils.py
lgdo/lh5/_serializers/read/vector_of_vectors.py
lgdo/lh5/_serializers/write/__init__.py
lgdo/lh5/_serializers/write/array.py
lgdo/lh5/_serializers/write/composite.py
lgdo/lh5/_serializers/write/scalar.py
lgdo/lh5/_serializers/write/vector_of_vectors.py
lgdo/types/__init__.py
lgdo/types/array.py
lgdo/types/arrayofequalsizedarrays.py
lgdo/types/encoded.py
lgdo/types/fixedsizearray.py
lgdo/types/histogram.py
lgdo/types/lgdo.py
lgdo/types/scalar.py
lgdo/types/struct.py
lgdo/types/table.py
lgdo/types/vectorofvectors.py
lgdo/types/vovutils.py
lgdo/types/waveformtable.py
legend_pydataobj-1.17.2.dist-info/METADATA
legend_pydataobj-1.17.2.dist-info/WHEEL
legend_pydataobj-1.17.2.dist-info/entry_points.txt
legend_pydataobj-1.17.2.dist-info/top_level.txt
legend_pydataobj-1.17.2.dist-info/RECORD
