Metadata-Version: 2.4
Name: legend_pydataobj
Version: 1.17.2
Summary: LEGEND Python Data Objects
Author: The LEGEND Collaboration
Maintainer: The LEGEND Collaboration
License-Expression: GPL-3.0
Project-URL: Homepage, https://github.com/legend-exp/legend-pydataobj
Project-URL: Bug Tracker, https://github.com/legend-exp/legend-pydataobj/issues
Project-URL: Discussions, https://github.com/legend-exp/legend-pydataobj/discussions
Project-URL: Changelog, https://github.com/legend-exp/legend-pydataobj/releases
Classifier: Development Status :: 4 - Beta
Classifier: Intended Audience :: Developers
Classifier: Intended Audience :: Science/Research
Classifier: Operating System :: MacOS
Classifier: Operating System :: POSIX
Classifier: Operating System :: Unix
Classifier: Programming Language :: Python
Classifier: Programming Language :: Python :: 3
Classifier: Programming Language :: Python :: 3 :: Only
Classifier: Topic :: Scientific/Engineering
Requires-Python: >=3.10
License-File: LICENSE
Requires-Dist: awkward>=2
Requires-Dist: awkward-pandas
Requires-Dist: colorlog
Requires-Dist: h5py>=3.10
Requires-Dist: hdf5plugin
Requires-Dist: hist
Requires-Dist: numba!=0.53.*,!=0.54.*
Requires-Dist: numexpr
Requires-Dist: numpy>=1.21
Requires-Dist: pandas>=1.4.4
Requires-Dist: parse
Requires-Dist: pint>0.24
Requires-Dist: pint-pandas
Provides-Extra: all
Requires-Dist: legend-pydataobj[docs,test]; extra == "all"
Provides-Extra: docs
Requires-Dist: furo; extra == "docs"
Requires-Dist: hist[plot]; extra == "docs"
Requires-Dist: jupyter; extra == "docs"
Requires-Dist: myst-parser; extra == "docs"
Requires-Dist: nbsphinx; extra == "docs"
Requires-Dist: sphinx; extra == "docs"
Requires-Dist: sphinx-copybutton; extra == "docs"
Requires-Dist: sphinx-inline-tabs; extra == "docs"
Provides-Extra: test
Requires-Dist: pre-commit; extra == "test"
Requires-Dist: pylegendtestdata; extra == "test"
Requires-Dist: pytest>=6.0; extra == "test"
Requires-Dist: pytest-cov; extra == "test"
Requires-Dist: dbetto; extra == "test"
Dynamic: license-file
